ccfg/__init__.py
ccfg-0.0.4.dist-info/licenses/LICENSE
ccfg-0.0.4.dist-info/METADATA
ccfg-0.0.4.dist-info/WHEEL
ccfg-0.0.4.dist-info/top_level.txt
ccfg-0.0.4.dist-info/RECORD
