Metadata-Version: 2.4
Name: ccfg
Version: 0.0.4
Summary: A Python library for managing hierarchical configurations using a class-based approach.
Author-email: Tanix <tanixlu@foxmail.com>
License-Expression: MIT
Project-URL: Homepage, https://github.com/TanixLu/ccfg
Keywords: config,class,pydantic,json
Classifier: Programming Language :: Python :: 3
Classifier: Operating System :: OS Independent
Requires-Python: >=3.6
License-File: LICENSE
Dynamic: license-file
